sanic_swagger_ui/__init__.py
sanic_swagger_ui/sanic_swagger_ui.py
sanic_swagger_ui/static/favicon-16x16.png
sanic_swagger_ui/static/favicon-32x32.png
sanic_swagger_ui/static/swagger-ui-bundle.js
sanic_swagger_ui/static/swagger-ui-es-bundle-core.js
sanic_swagger_ui/static/swagger-ui-es-bundle.js
sanic_swagger_ui/static/swagger-ui-standalone-preset.js
sanic_swagger_ui/static/swagger-ui.css
sanic_swagger_ui/static/swagger-ui.js
sanic_swagger_ui/templates/index.html
sanic_swagger_ui-0.0.2.dist-info/METADATA
sanic_swagger_ui-0.0.2.dist-info/WHEEL
sanic_swagger_ui-0.0.2.dist-info/top_level.txt
sanic_swagger_ui-0.0.2.dist-info/RECORD
