Metadata-Version: 2.1
Name: sanic-swagger-ui
Version: 0.0.2
Summary: Swagger UI blueprint for Sanic
Home-page: https://github.com/diptangsu/sanic-swagger-ui
Author: Diptangsu Goswami
Author-email: diptangsu.97@gmail.com
License: MIT
Keywords: sanic swagger
Platform: UNKNOWN
Classifier: Intended Audience :: Developers
Classifier: License :: OSI Approved :: MIT License
Classifier: Programming Language :: Python :: 3
Classifier: Programming Language :: Python :: 3.6
Classifier: Programming Language :: Python :: 3.7
Classifier: Programming Language :: Python :: 3.8
Requires-Dist: jinja2
Requires-Dist: sanic
